{
  "AppTitle": "SharpCoreDB Viewer",
  "Connect": "Verbinden",
  "Disconnect": "Verbindung trennen",
  "Execute": "Ausführen",
  "NotConnected": "Nicht verbunden",
  "DatabaseTables": "Datenbanktabellen",
  "QueryEditor": "SQL Query Editor",
  "QueryResults": "Abfrageergebnisse",
  "Ready": "Bereit",
  "WelcomeTitle": "SharpCoreDB Viewer",
  "WelcomeMessage": "Klicken Sie auf 'Verbinden', um eine Datenbank zu öffnen",
  "ConnectToDatabase": "Mit Datenbank verbinden",
  "QueryPlaceholder": "SQL-Abfrage hier eingeben...",
  "ResultsPlaceholder": "Führen Sie eine Abfrage aus, um Ergebnisse zu sehen",
  "ConnectionDialogTitle": "Mit SharpCoreDB verbinden",
  "ConnectionDialogSubtitle": "Öffnen Sie eine vorhandene Datenbank oder erstellen Sie eine neue",
  "DatabasePath": "Datenbankpfad:",
  "DatabasePathPlaceholder": "C:\\data\\meinedb.scdb oder Datenbankverzeichnis",
  "Browse": "Durchsuchen...",
  "New": "Neu...",
  "MasterPassword": "Hauptkennwort:",
  "PasswordPlaceholder": "Datenbankkennwort eingeben",
  "Cancel": "Abbrechen",
  "Connecting": "Verbinde...",
  "Save": "Speichern",
  "ConnectTooltip": "Mit vorhandener Datenbank verbinden",
  "DisconnectTooltip": "Verbindung zur Datenbank trennen",
  "ExecuteTooltip": "SQL-Abfrage ausführen (F5)",
  "BrowseTooltip": "Nach vorhandener Datenbank suchen",
  "NewTooltip": "Neue Datenbank erstellen",
  "ErrorDatabasePathRequired": "Bitte geben Sie einen Datenbankpfad ein",
  "ErrorPasswordRequired": "Bitte geben Sie ein Kennwort ein",
  "ErrorDatabaseNotFound": "Datenbankpfad existiert nicht",
  "ErrorConnectionFailed": "Verbindung fehlgeschlagen: {0}",
  "ErrorIncorrectPassword": "⚠️ Falsches Kennwort oder beschädigte Datenbank. Bitte überprüfen Sie Ihr Kennwort und versuchen Sie es erneut.",
  "ErrorTableLoadFailed": "Laden der Tabellen fehlgeschlagen: {0}",
  "ConnectedTo": "Verbunden mit: {0}",
  "SelectNewDatabaseLocation": "Speicherort für neue SharpCoreDB-Datenbank auswählen",
  "SettingsTitle": "Einstellungen",
  "LanguageLabel": "Sprache",
  "LanguageDescription": "Änderungen werden sofort angewendet. Klicken Sie auf 'Einstellungen speichern', um Ihre Auswahl beim nächsten Start zu speichern.",
  "ThemeLabel": "Design",
  "ThemeDescription": "Umschalten zur Vorschau. Klicken Sie auf 'Einstellungen speichern', um Ihre Auswahl beim nächsten Start zu speichern.",
  "FileMenu": "Datei",
  "SettingsMenu": "Einstellungen",
  "ExitMenu": "Beenden",
  "ShowPassword": "Kennwort anzeigen",
  "HidePassword": "Kennwort verbergen",
  "ErrorQueryEmpty": "Bitte geben Sie eine SQL-Abfrage ein",
  "ExecutingQuery": "Abfrage wird ausgeführt...",
  "QueryExecutedSuccess": "Abfrage erfolgreich ausgeführt. {0} Zeilen zurückgegeben.",
  "QueryExecutedAffected": "{0} Zeilen betroffen.",
  "ErrorQueryFailed": "Abfrage fehlgeschlagen: {0}",
  "ToolsMenu": "Werkzeuge",
  "ToolsTitle": "Datenbank-Werkzeuge",
  "ToolsSubtitle": "Datenbankformate konvertieren und Wartungsaufgaben durchführen",
  "DatabaseFormat": "Datenbankformat:",
  "FormatDirectory": "Verzeichnis (Mehrere Dateien)",
  "FormatDirectoryDesc": "Traditionelles Format mit separaten Dateien pro Tabelle",
  "FormatSingleFile": "Einzelne Datei (.scdb)",
  "FormatSingleFileDesc": "Modernes Format mit allen Daten in einer Datei",
  "SourceDatabase": "Quelldatenbank",
  "TargetDatabase": "Zieldatenbank",
  "SourceFormat": "Quellformat",
  "TargetFormat": "Zielformat",
  "SourcePath": "Quellpfad:",
  "TargetPath": "Zielpfad:",
  "SourcePathPlaceholder": "Quelldatenbank auswählen...",
  "TargetPathPlaceholder": "Zieldatenbank auswählen...",
  "Convert": "Konvertieren",
  "Close": "Schließen",
  "BrowseSourceDatabase": "Nach Quelldatenbank suchen",
  "BrowseTargetDatabase": "Nach Zieldatenbank suchen",
  "SwapFormats": "Quell- und Zielformate tauschen",
  "ConversionProgress": "Konvertierungsfortschritt",
  "ConvertingDatabase": "Datenbank wird konvertiert...",
  "ConvertingProgress": "Konvertiere... {0}%",
  "ConversionComplete": "✅ Konvertierung erfolgreich abgeschlossen!",
  "ErrorSourcePathRequired": "Bitte wählen Sie eine Quelldatenbank",
  "ErrorTargetPathRequired": "Bitte wählen Sie eine Zieldatenbank",
  "ErrorSourceNotFound": "Quelldatenbank nicht gefunden",
  "ErrorSameFormat": "Quell- und Zielformat müssen unterschiedlich sein",
  "ErrorConversionFailed": "Konvertierung fehlgeschlagen: {0}"
}
